README.rst
setup.py
BasicCalculator.egg-info/PKG-INFO
BasicCalculator.egg-info/SOURCES.txt
BasicCalculator.egg-info/dependency_links.txt
BasicCalculator.egg-info/entry_points.txt
BasicCalculator.egg-info/top_level.txt
Calculator/__init__.py
Calculator/calculator.py