Metadata-Version: 1.0
Name: BasicCalculator
Version: 0.2
Summary: A simple calculator app
Home-page: https://github.com/Urosh91/Bitcoin-Value
Author: Uroš Jevremović
Author-email: jevremovic.uros91@gmail.com
License: UNKNOWN
Platform: UNKNOWN
